[
null,
{"id":1,"members":[{"enemyId":1,"x":675,"y":444,"hidden":false}],"name":"EVENT","pages":[{"conditions":{"actorHp":50,"actorId":1,"actorValid":false,"enemyHp":50,"enemyIndex":0,"enemyValid":false,"switchId":1,"switchValid":false,"turnA":0,"turnB":0,"turnEnding":false,"turnValid":true},"list":[{"code":117,"indent":0,"parameters":[200]},{"code":0,"indent":0,"parameters":[]}],"span":0}]},
{"id":2,"members":[{"enemyId":1,"x":681,"y":444,"hidden":false}],"name":"ENEMY","pages":[{"conditions":{"actorHp":50,"actorId":1,"actorValid":false,"enemyHp":50,"enemyIndex":0,"enemyValid":false,"switchId":1,"switchValid":false,"turnA":0,"turnB":0,"turnEnding":false,"turnValid":true},"list":[{"code":0,"indent":0,"parameters":[]}],"span":0}]},
{"id":3,"members":[{"enemyId":4,"x":384,"y":444,"hidden":false}],"name":"Mad Vessel","pages":[{"conditions":{"actorHp":1,"actorId":8,"actorValid":false,"enemyHp":50,"enemyIndex":0,"enemyValid":false,"switchId":1,"switchValid":false,"turnA":0,"turnB":0,"turnEnding":false,"turnValid":true},"list":[{"code":111,"indent":0,"parameters":[0,90,0]},{"code":0,"indent":1,"parameters":[]},{"code":411,"indent":0,"parameters":[]},{"code":101,"indent":1,"parameters":["",0,2,1]},{"code":401,"indent":1,"parameters":["\\c[1]{EnemyEncounter1}"]},{"code":121,"indent":1,"parameters":[90,90,0]},{"code":224,"indent":1,"parameters":[[255,0,0,187],200,false]},{"code":0,"indent":1,"parameters":[]},{"code":412,"indent":0,"parameters":[]},{"code":0,"indent":0,"parameters":[]}],"span":0},{"conditions":{"actorHp":50,"actorId":1,"actorValid":false,"enemyHp":5,"enemyIndex":0,"enemyValid":true,"switchId":1,"switchValid":false,"turnA":0,"turnB":0,"turnEnding":false,"turnValid":false},"list":[{"code":331,"indent":0,"parameters":[-1,1,0,9999,true]},{"code":223,"indent":0,"parameters":[[0,0,0,0],60,false]},{"code":121,"indent":0,"parameters":[89,89,1]},{"code":250,"indent":0,"parameters":[{"name":"SE_Scream3","volume":90,"pitch":100,"pan":0}]},{"code":0,"indent":0,"parameters":[]}],"span":0},{"conditions":{"actorHp":50,"actorId":1,"actorValid":false,"enemyHp":50,"enemyIndex":0,"enemyValid":false,"switchId":89,"switchValid":true,"turnA":0,"turnB":0,"turnEnding":false,"turnValid":false},"list":[{"code":111,"indent":0,"parameters":[1,2,0,1,0]},{"code":339,"indent":1,"parameters":[1,1,1,-1]},{"code":0,"indent":1,"parameters":[]},{"code":411,"indent":0,"parameters":[]},{"code":111,"indent":1,"parameters":[1,2,0,2,0]},{"code":339,"indent":2,"parameters":[1,2,1,-1]},{"code":0,"indent":2,"parameters":[]},{"code":411,"indent":1,"parameters":[]},{"code":111,"indent":2,"parameters":[1,2,0,5,0]},{"code":339,"indent":3,"parameters":[1,5,1,-1]},{"code":0,"indent":3,"parameters":[]},{"code":411,"indent":2,"parameters":[]},{"code":111,"indent":3,"parameters":[1,2,0,6,0]},{"code":339,"indent":4,"parameters":[1,6,1,-1]},{"code":0,"indent":4,"parameters":[]},{"code":412,"indent":3,"parameters":[]},{"code":0,"indent":3,"parameters":[]},{"code":412,"indent":2,"parameters":[]},{"code":0,"indent":2,"parameters":[]},{"code":412,"indent":1,"parameters":[]},{"code":0,"indent":1,"parameters":[]},{"code":412,"indent":0,"parameters":[]},{"code":230,"indent":0,"parameters":[30]},{"code":121,"indent":0,"parameters":[89,89,1]},{"code":0,"indent":0,"parameters":[]}],"span":0},{"conditions":{"actorHp":50,"actorId":1,"actorValid":false,"enemyHp":50,"enemyIndex":0,"enemyValid":false,"switchId":1,"switchValid":false,"turnA":0,"turnB":0,"turnEnding":false,"turnValid":true},"list":[{"code":122,"indent":0,"parameters":[19,19,0,3,3,1,0]},{"code":111,"indent":0,"parameters":[1,19,0,0,0]},{"code":333,"indent":1,"parameters":[-1,0,210]},{"code":0,"indent":1,"parameters":[]},{"code":412,"indent":0,"parameters":[]},{"code":111,"indent":0,"parameters":[0,4818,0]},{"code":331,"indent":1,"parameters":[1,1,0,200,false]},{"code":0,"indent":1,"parameters":[]},{"code":412,"indent":0,"parameters":[]},{"code":0,"indent":0,"parameters":[]}],"span":0}]},
{"id":4,"members":[{"enemyId":5,"x":558,"y":444,"hidden":false}],"name":"Mutated parasite","pages":[{"conditions":{"actorHp":50,"actorId":1,"actorValid":false,"enemyHp":50,"enemyIndex":0,"enemyValid":false,"switchId":1,"switchValid":false,"turnA":0,"turnB":0,"turnEnding":false,"turnValid":true},"list":[{"code":111,"indent":0,"parameters":[0,91,0]},{"code":0,"indent":1,"parameters":[]},{"code":411,"indent":0,"parameters":[]},{"code":101,"indent":1,"parameters":["",0,2,1]},{"code":401,"indent":1,"parameters":["\\c[1]{EnemyEncounter2}"]},{"code":121,"indent":1,"parameters":[91,91,0]},{"code":224,"indent":1,"parameters":[[255,0,0,187],200,false]},{"code":0,"indent":1,"parameters":[]},{"code":412,"indent":0,"parameters":[]},{"code":0,"indent":0,"parameters":[]}],"span":0},{"conditions":{"actorHp":50,"actorId":1,"actorValid":false,"enemyHp":5,"enemyIndex":0,"enemyValid":true,"switchId":1,"switchValid":false,"turnA":0,"turnB":0,"turnEnding":false,"turnValid":false},"list":[{"code":331,"indent":0,"parameters":[-1,1,0,9999,true]},{"code":223,"indent":0,"parameters":[[0,0,0,0],60,false]},{"code":121,"indent":0,"parameters":[89,89,1]},{"code":250,"indent":0,"parameters":[{"name":"SE_DeathEnemy","volume":100,"pitch":50,"pan":0}]},{"code":0,"indent":0,"parameters":[]}],"span":0},{"conditions":{"actorHp":50,"actorId":1,"actorValid":false,"enemyHp":50,"enemyIndex":0,"enemyValid":false,"switchId":89,"switchValid":true,"turnA":0,"turnB":0,"turnEnding":false,"turnValid":false},"list":[{"code":111,"indent":0,"parameters":[1,2,0,1,0]},{"code":339,"indent":1,"parameters":[1,1,1,-1]},{"code":0,"indent":1,"parameters":[]},{"code":411,"indent":0,"parameters":[]},{"code":111,"indent":1,"parameters":[1,2,0,2,0]},{"code":339,"indent":2,"parameters":[1,2,1,-1]},{"code":0,"indent":2,"parameters":[]},{"code":411,"indent":1,"parameters":[]},{"code":111,"indent":2,"parameters":[1,2,0,5,0]},{"code":339,"indent":3,"parameters":[1,5,1,-1]},{"code":0,"indent":3,"parameters":[]},{"code":411,"indent":2,"parameters":[]},{"code":111,"indent":3,"parameters":[1,2,0,6,0]},{"code":339,"indent":4,"parameters":[1,6,1,-1]},{"code":0,"indent":4,"parameters":[]},{"code":412,"indent":3,"parameters":[]},{"code":0,"indent":3,"parameters":[]},{"code":412,"indent":2,"parameters":[]},{"code":0,"indent":2,"parameters":[]},{"code":412,"indent":1,"parameters":[]},{"code":0,"indent":1,"parameters":[]},{"code":412,"indent":0,"parameters":[]},{"code":230,"indent":0,"parameters":[30]},{"code":121,"indent":0,"parameters":[89,89,1]},{"code":0,"indent":0,"parameters":[]}],"span":0}]},
{"id":5,"members":[{"enemyId":6,"x":217,"y":405,"hidden":false}],"name":"Pure Vessel","pages":[{"conditions":{"actorHp":1,"actorId":8,"actorValid":false,"enemyHp":50,"enemyIndex":0,"enemyValid":false,"switchId":1,"switchValid":false,"turnA":0,"turnB":0,"turnEnding":false,"turnValid":true},"list":[{"code":111,"indent":0,"parameters":[0,90,0]},{"code":0,"indent":1,"parameters":[]},{"code":411,"indent":0,"parameters":[]},{"code":101,"indent":1,"parameters":["",0,2,1]},{"code":401,"indent":1,"parameters":["\\c[1]{EnemyEncounter3}"]},{"code":121,"indent":1,"parameters":[90,90,0]},{"code":224,"indent":1,"parameters":[[255,0,0,187],200,false]},{"code":0,"indent":1,"parameters":[]},{"code":412,"indent":0,"parameters":[]},{"code":0,"indent":0,"parameters":[]}],"span":0},{"conditions":{"actorHp":50,"actorId":1,"actorValid":false,"enemyHp":5,"enemyIndex":0,"enemyValid":true,"switchId":1,"switchValid":false,"turnA":0,"turnB":0,"turnEnding":false,"turnValid":false},"list":[{"code":331,"indent":0,"parameters":[-1,1,0,9999,true]},{"code":223,"indent":0,"parameters":[[0,0,0,0],60,false]},{"code":121,"indent":0,"parameters":[89,89,1]},{"code":250,"indent":0,"parameters":[{"name":"SE_Screamer2 (1)","volume":100,"pitch":110,"pan":0}]},{"code":0,"indent":0,"parameters":[]}],"span":0},{"conditions":{"actorHp":50,"actorId":1,"actorValid":false,"enemyHp":50,"enemyIndex":0,"enemyValid":false,"switchId":89,"switchValid":true,"turnA":0,"turnB":0,"turnEnding":false,"turnValid":false},"list":[{"code":111,"indent":0,"parameters":[1,2,0,1,0]},{"code":339,"indent":1,"parameters":[1,1,1,-1]},{"code":0,"indent":1,"parameters":[]},{"code":411,"indent":0,"parameters":[]},{"code":111,"indent":1,"parameters":[1,2,0,2,0]},{"code":339,"indent":2,"parameters":[1,2,1,-1]},{"code":0,"indent":2,"parameters":[]},{"code":411,"indent":1,"parameters":[]},{"code":111,"indent":2,"parameters":[1,2,0,5,0]},{"code":339,"indent":3,"parameters":[1,5,1,-1]},{"code":0,"indent":3,"parameters":[]},{"code":411,"indent":2,"parameters":[]},{"code":111,"indent":3,"parameters":[1,2,0,6,0]},{"code":339,"indent":4,"parameters":[1,6,1,-1]},{"code":0,"indent":4,"parameters":[]},{"code":412,"indent":3,"parameters":[]},{"code":0,"indent":3,"parameters":[]},{"code":412,"indent":2,"parameters":[]},{"code":0,"indent":2,"parameters":[]},{"code":412,"indent":1,"parameters":[]},{"code":0,"indent":1,"parameters":[]},{"code":412,"indent":0,"parameters":[]},{"code":230,"indent":0,"parameters":[30]},{"code":121,"indent":0,"parameters":[89,89,1]},{"code":0,"indent":0,"parameters":[]}],"span":0}]},
{"id":6,"members":[{"enemyId":7,"x":463,"y":288,"hidden":false}],"name":"Dandelo","pages":[{"conditions":{"actorHp":1,"actorId":8,"actorValid":false,"enemyHp":50,"enemyIndex":0,"enemyValid":false,"switchId":1,"switchValid":false,"turnA":0,"turnB":0,"turnEnding":false,"turnValid":true},"list":[{"code":111,"indent":0,"parameters":[0,94,0]},{"code":0,"indent":1,"parameters":[]},{"code":411,"indent":0,"parameters":[]},{"code":101,"indent":1,"parameters":["",0,2,1]},{"code":401,"indent":1,"parameters":["\\c[1]{EnemyEncounter5}"]},{"code":121,"indent":1,"parameters":[94,94,0]},{"code":224,"indent":1,"parameters":[[255,0,0,187],200,false]},{"code":0,"indent":1,"parameters":[]},{"code":412,"indent":0,"parameters":[]},{"code":0,"indent":0,"parameters":[]}],"span":0},{"conditions":{"actorHp":50,"actorId":1,"actorValid":false,"enemyHp":5,"enemyIndex":0,"enemyValid":true,"switchId":1,"switchValid":false,"turnA":0,"turnB":0,"turnEnding":false,"turnValid":false},"list":[{"code":331,"indent":0,"parameters":[-1,1,0,9999,true]},{"code":223,"indent":0,"parameters":[[0,0,0,0],60,false]},{"code":121,"indent":0,"parameters":[89,89,1]},{"code":250,"indent":0,"parameters":[{"name":"SE_DeathEnemy","volume":100,"pitch":100,"pan":0}]},{"code":0,"indent":0,"parameters":[]}],"span":0},{"conditions":{"actorHp":50,"actorId":1,"actorValid":false,"enemyHp":50,"enemyIndex":0,"enemyValid":false,"switchId":89,"switchValid":true,"turnA":0,"turnB":0,"turnEnding":false,"turnValid":false},"list":[{"code":111,"indent":0,"parameters":[1,2,0,1,0]},{"code":339,"indent":1,"parameters":[1,1,1,-1]},{"code":0,"indent":1,"parameters":[]},{"code":411,"indent":0,"parameters":[]},{"code":111,"indent":1,"parameters":[1,2,0,2,0]},{"code":339,"indent":2,"parameters":[1,2,1,-1]},{"code":0,"indent":2,"parameters":[]},{"code":411,"indent":1,"parameters":[]},{"code":111,"indent":2,"parameters":[1,2,0,5,0]},{"code":339,"indent":3,"parameters":[1,5,1,-1]},{"code":0,"indent":3,"parameters":[]},{"code":411,"indent":2,"parameters":[]},{"code":111,"indent":3,"parameters":[1,2,0,6,0]},{"code":339,"indent":4,"parameters":[1,6,1,-1]},{"code":0,"indent":4,"parameters":[]},{"code":412,"indent":3,"parameters":[]},{"code":0,"indent":3,"parameters":[]},{"code":412,"indent":2,"parameters":[]},{"code":0,"indent":2,"parameters":[]},{"code":412,"indent":1,"parameters":[]},{"code":0,"indent":1,"parameters":[]},{"code":412,"indent":0,"parameters":[]},{"code":230,"indent":0,"parameters":[30]},{"code":121,"indent":0,"parameters":[89,89,1]},{"code":0,"indent":0,"parameters":[]}],"span":0}]},
{"id":7,"members":[{"enemyId":8,"x":214,"y":384,"hidden":false}],"name":"Head of the cult","pages":[{"conditions":{"actorHp":1,"actorId":8,"actorValid":false,"enemyHp":50,"enemyIndex":0,"enemyValid":false,"switchId":1,"switchValid":false,"turnA":0,"turnB":0,"turnEnding":false,"turnValid":true},"list":[{"code":128,"indent":0,"parameters":[51,0,0,6,false]},{"code":111,"indent":0,"parameters":[0,94,0]},{"code":0,"indent":1,"parameters":[]},{"code":411,"indent":0,"parameters":[]},{"code":101,"indent":1,"parameters":["",0,2,1]},{"code":401,"indent":1,"parameters":["\\c[1]{EnemyEncounter5}"]},{"code":121,"indent":1,"parameters":[94,94,0]},{"code":224,"indent":1,"parameters":[[255,0,0,187],200,false]},{"code":0,"indent":1,"parameters":[]},{"code":412,"indent":0,"parameters":[]},{"code":0,"indent":0,"parameters":[]}],"span":0},{"conditions":{"actorHp":50,"actorId":1,"actorValid":false,"enemyHp":5,"enemyIndex":0,"enemyValid":true,"switchId":1,"switchValid":false,"turnA":0,"turnB":0,"turnEnding":false,"turnValid":false},"list":[{"code":331,"indent":0,"parameters":[-1,1,0,9999,true]},{"code":223,"indent":0,"parameters":[[0,0,0,0],60,false]},{"code":121,"indent":0,"parameters":[89,89,1]},{"code":250,"indent":0,"parameters":[{"name":"SE_DeathEnemy","volume":100,"pitch":100,"pan":0}]},{"code":0,"indent":0,"parameters":[]}],"span":0},{"conditions":{"actorHp":50,"actorId":1,"actorValid":false,"enemyHp":50,"enemyIndex":0,"enemyValid":false,"switchId":89,"switchValid":true,"turnA":0,"turnB":0,"turnEnding":false,"turnValid":false},"list":[{"code":111,"indent":0,"parameters":[1,2,0,1,0]},{"code":339,"indent":1,"parameters":[1,1,1,-1]},{"code":0,"indent":1,"parameters":[]},{"code":411,"indent":0,"parameters":[]},{"code":111,"indent":1,"parameters":[1,2,0,2,0]},{"code":339,"indent":2,"parameters":[1,2,1,-1]},{"code":0,"indent":2,"parameters":[]},{"code":411,"indent":1,"parameters":[]},{"code":111,"indent":2,"parameters":[1,2,0,5,0]},{"code":339,"indent":3,"parameters":[1,5,1,-1]},{"code":0,"indent":3,"parameters":[]},{"code":411,"indent":2,"parameters":[]},{"code":111,"indent":3,"parameters":[1,2,0,6,0]},{"code":339,"indent":4,"parameters":[1,6,1,-1]},{"code":0,"indent":4,"parameters":[]},{"code":412,"indent":3,"parameters":[]},{"code":0,"indent":3,"parameters":[]},{"code":412,"indent":2,"parameters":[]},{"code":0,"indent":2,"parameters":[]},{"code":412,"indent":1,"parameters":[]},{"code":0,"indent":1,"parameters":[]},{"code":412,"indent":0,"parameters":[]},{"code":230,"indent":0,"parameters":[30]},{"code":121,"indent":0,"parameters":[89,89,1]},{"code":0,"indent":0,"parameters":[]}],"span":0}]},
{"id":8,"members":[{"enemyId":9,"x":685,"y":444,"hidden":false}],"name":"Bloody mess","pages":[{"conditions":{"actorHp":1,"actorId":8,"actorValid":false,"enemyHp":50,"enemyIndex":0,"enemyValid":false,"switchId":1,"switchValid":false,"turnA":0,"turnB":0,"turnEnding":false,"turnValid":true},"list":[{"code":111,"indent":0,"parameters":[0,93,0]},{"code":0,"indent":1,"parameters":[]},{"code":411,"indent":0,"parameters":[]},{"code":101,"indent":1,"parameters":["",0,2,1]},{"code":401,"indent":1,"parameters":["\\c[1]{EnemyEncounter4}"]},{"code":121,"indent":1,"parameters":[93,93,0]},{"code":224,"indent":1,"parameters":[[255,0,0,187],200,false]},{"code":0,"indent":1,"parameters":[]},{"code":412,"indent":0,"parameters":[]},{"code":0,"indent":0,"parameters":[]}],"span":0},{"conditions":{"actorHp":50,"actorId":1,"actorValid":false,"enemyHp":5,"enemyIndex":0,"enemyValid":true,"switchId":1,"switchValid":false,"turnA":0,"turnB":0,"turnEnding":false,"turnValid":false},"list":[{"code":331,"indent":0,"parameters":[-1,1,0,9999,true]},{"code":223,"indent":0,"parameters":[[0,0,0,0],60,false]},{"code":121,"indent":0,"parameters":[89,89,1]},{"code":250,"indent":0,"parameters":[{"name":"SE_DeathEnemy","volume":100,"pitch":80,"pan":0}]},{"code":0,"indent":0,"parameters":[]}],"span":0},{"conditions":{"actorHp":50,"actorId":1,"actorValid":false,"enemyHp":50,"enemyIndex":0,"enemyValid":false,"switchId":89,"switchValid":true,"turnA":0,"turnB":0,"turnEnding":false,"turnValid":false},"list":[{"code":111,"indent":0,"parameters":[1,2,0,1,0]},{"code":339,"indent":1,"parameters":[1,1,1,-1]},{"code":0,"indent":1,"parameters":[]},{"code":411,"indent":0,"parameters":[]},{"code":111,"indent":1,"parameters":[1,2,0,2,0]},{"code":339,"indent":2,"parameters":[1,2,1,-1]},{"code":0,"indent":2,"parameters":[]},{"code":411,"indent":1,"parameters":[]},{"code":111,"indent":2,"parameters":[1,2,0,5,0]},{"code":339,"indent":3,"parameters":[1,5,1,-1]},{"code":0,"indent":3,"parameters":[]},{"code":411,"indent":2,"parameters":[]},{"code":111,"indent":3,"parameters":[1,2,0,6,0]},{"code":339,"indent":4,"parameters":[1,6,1,-1]},{"code":0,"indent":4,"parameters":[]},{"code":412,"indent":3,"parameters":[]},{"code":0,"indent":3,"parameters":[]},{"code":412,"indent":2,"parameters":[]},{"code":0,"indent":2,"parameters":[]},{"code":412,"indent":1,"parameters":[]},{"code":0,"indent":1,"parameters":[]},{"code":412,"indent":0,"parameters":[]},{"code":230,"indent":0,"parameters":[30]},{"code":121,"indent":0,"parameters":[89,89,1]},{"code":0,"indent":0,"parameters":[]}],"span":0}]},
{"id":9,"members":[{"enemyId":10,"x":370,"y":216,"hidden":false}],"name":"Statue","pages":[{"conditions":{"actorHp":50,"actorId":1,"actorValid":false,"enemyHp":50,"enemyIndex":0,"enemyValid":false,"switchId":1,"switchValid":false,"turnA":0,"turnB":0,"turnEnding":false,"turnValid":true},"list":[{"code":0,"indent":0,"parameters":[]}],"span":0},{"conditions":{"actorHp":50,"actorId":1,"actorValid":false,"enemyHp":5,"enemyIndex":0,"enemyValid":true,"switchId":1,"switchValid":false,"turnA":0,"turnB":0,"turnEnding":false,"turnValid":false},"list":[{"code":331,"indent":0,"parameters":[-1,1,0,9999,true]},{"code":223,"indent":0,"parameters":[[0,0,0,0],60,false]},{"code":121,"indent":0,"parameters":[89,89,1]},{"code":250,"indent":0,"parameters":[{"name":"SE_DeathEnemy","volume":100,"pitch":100,"pan":0}]},{"code":0,"indent":0,"parameters":[]}],"span":0},{"conditions":{"actorHp":50,"actorId":1,"actorValid":false,"enemyHp":50,"enemyIndex":0,"enemyValid":false,"switchId":89,"switchValid":true,"turnA":0,"turnB":0,"turnEnding":false,"turnValid":false},"list":[{"code":111,"indent":0,"parameters":[1,2,0,1,0]},{"code":339,"indent":1,"parameters":[1,1,1,-1]},{"code":0,"indent":1,"parameters":[]},{"code":411,"indent":0,"parameters":[]},{"code":111,"indent":1,"parameters":[1,2,0,2,0]},{"code":339,"indent":2,"parameters":[1,2,1,-1]},{"code":0,"indent":2,"parameters":[]},{"code":411,"indent":1,"parameters":[]},{"code":111,"indent":2,"parameters":[1,2,0,5,0]},{"code":339,"indent":3,"parameters":[1,5,1,-1]},{"code":0,"indent":3,"parameters":[]},{"code":411,"indent":2,"parameters":[]},{"code":111,"indent":3,"parameters":[1,2,0,6,0]},{"code":339,"indent":4,"parameters":[1,6,1,-1]},{"code":0,"indent":4,"parameters":[]},{"code":412,"indent":3,"parameters":[]},{"code":0,"indent":3,"parameters":[]},{"code":412,"indent":2,"parameters":[]},{"code":0,"indent":2,"parameters":[]},{"code":412,"indent":1,"parameters":[]},{"code":0,"indent":1,"parameters":[]},{"code":412,"indent":0,"parameters":[]},{"code":230,"indent":0,"parameters":[30]},{"code":121,"indent":0,"parameters":[89,89,1]},{"code":0,"indent":0,"parameters":[]}],"span":0}]},
{"id":10,"members":[{"enemyId":11,"x":403,"y":192,"hidden":false}],"name":"Butcher","pages":[{"conditions":{"actorHp":50,"actorId":1,"actorValid":false,"enemyHp":75,"enemyIndex":0,"enemyValid":true,"switchId":1,"switchValid":false,"turnA":0,"turnB":0,"turnEnding":false,"turnValid":false},"list":[{"code":108,"indent":0,"parameters":["Enemy DESTROYED"]},{"code":224,"indent":0,"parameters":[[255,0,0,170],200,false]},{"code":250,"indent":0,"parameters":[{"name":"SE_ButcherLaught","volume":100,"pitch":90,"pan":0}]},{"code":250,"indent":0,"parameters":[{"name":"SE_Monster","volume":90,"pitch":100,"pan":0}]},{"code":223,"indent":0,"parameters":[[34,-68,-68,0],60,false]},{"code":336,"indent":0,"parameters":[0,12]},{"code":0,"indent":0,"parameters":[]}],"span":0},{"conditions":{"actorHp":50,"actorId":1,"actorValid":false,"enemyHp":50,"enemyIndex":0,"enemyValid":false,"switchId":1,"switchValid":false,"turnA":0,"turnB":0,"turnEnding":false,"turnValid":true},"list":[{"code":117,"indent":0,"parameters":[408]},{"code":0,"indent":0,"parameters":[]}],"span":0},{"conditions":{"actorHp":50,"actorId":1,"actorValid":false,"enemyHp":5,"enemyIndex":0,"enemyValid":true,"switchId":1,"switchValid":false,"turnA":0,"turnB":0,"turnEnding":false,"turnValid":false},"list":[{"code":331,"indent":0,"parameters":[-1,1,0,9999,true]},{"code":223,"indent":0,"parameters":[[0,0,0,0],60,false]},{"code":121,"indent":0,"parameters":[89,89,1]},{"code":250,"indent":0,"parameters":[{"name":"SE_DeathEnemy","volume":100,"pitch":100,"pan":0}]},{"code":0,"indent":0,"parameters":[]}],"span":0},{"conditions":{"actorHp":50,"actorId":1,"actorValid":false,"enemyHp":50,"enemyIndex":0,"enemyValid":false,"switchId":89,"switchValid":true,"turnA":0,"turnB":0,"turnEnding":false,"turnValid":false},"list":[{"code":111,"indent":0,"parameters":[1,2,0,1,0]},{"code":339,"indent":1,"parameters":[1,1,1,-1]},{"code":0,"indent":1,"parameters":[]},{"code":411,"indent":0,"parameters":[]},{"code":111,"indent":1,"parameters":[1,2,0,2,0]},{"code":339,"indent":2,"parameters":[1,2,1,-1]},{"code":0,"indent":2,"parameters":[]},{"code":411,"indent":1,"parameters":[]},{"code":111,"indent":2,"parameters":[1,2,0,5,0]},{"code":339,"indent":3,"parameters":[1,5,1,-1]},{"code":0,"indent":3,"parameters":[]},{"code":411,"indent":2,"parameters":[]},{"code":111,"indent":3,"parameters":[1,2,0,6,0]},{"code":339,"indent":4,"parameters":[1,6,1,-1]},{"code":0,"indent":4,"parameters":[]},{"code":412,"indent":3,"parameters":[]},{"code":0,"indent":3,"parameters":[]},{"code":412,"indent":2,"parameters":[]},{"code":0,"indent":2,"parameters":[]},{"code":412,"indent":1,"parameters":[]},{"code":0,"indent":1,"parameters":[]},{"code":412,"indent":0,"parameters":[]},{"code":230,"indent":0,"parameters":[30]},{"code":121,"indent":0,"parameters":[89,89,1]},{"code":0,"indent":0,"parameters":[]}],"span":0}]},
{"id":11,"members":[{"enemyId":13,"x":463,"y":444,"hidden":false}],"name":"August","pages":[{"conditions":{"actorHp":50,"actorId":1,"actorValid":false,"enemyHp":50,"enemyIndex":0,"enemyValid":false,"switchId":1,"switchValid":false,"turnA":0,"turnB":0,"turnEnding":false,"turnValid":true},"list":[{"code":117,"indent":0,"parameters":[408]},{"code":0,"indent":0,"parameters":[]}],"span":0},{"conditions":{"actorHp":50,"actorId":1,"actorValid":false,"enemyHp":5,"enemyIndex":0,"enemyValid":true,"switchId":1,"switchValid":false,"turnA":0,"turnB":0,"turnEnding":false,"turnValid":false},"list":[{"code":331,"indent":0,"parameters":[-1,1,0,9999,true]},{"code":223,"indent":0,"parameters":[[0,0,0,0],60,false]},{"code":121,"indent":0,"parameters":[89,89,1]},{"code":250,"indent":0,"parameters":[{"name":"SE_Scream3","volume":100,"pitch":90,"pan":0}]},{"code":0,"indent":0,"parameters":[]}],"span":0},{"conditions":{"actorHp":50,"actorId":1,"actorValid":false,"enemyHp":50,"enemyIndex":0,"enemyValid":false,"switchId":89,"switchValid":true,"turnA":0,"turnB":0,"turnEnding":false,"turnValid":false},"list":[{"code":111,"indent":0,"parameters":[1,2,0,1,0]},{"code":339,"indent":1,"parameters":[1,1,1,-1]},{"code":0,"indent":1,"parameters":[]},{"code":411,"indent":0,"parameters":[]},{"code":111,"indent":1,"parameters":[1,2,0,2,0]},{"code":339,"indent":2,"parameters":[1,2,1,-1]},{"code":0,"indent":2,"parameters":[]},{"code":411,"indent":1,"parameters":[]},{"code":111,"indent":2,"parameters":[1,2,0,5,0]},{"code":339,"indent":3,"parameters":[1,5,1,-1]},{"code":0,"indent":3,"parameters":[]},{"code":411,"indent":2,"parameters":[]},{"code":111,"indent":3,"parameters":[1,2,0,6,0]},{"code":339,"indent":4,"parameters":[1,6,1,-1]},{"code":0,"indent":4,"parameters":[]},{"code":412,"indent":3,"parameters":[]},{"code":0,"indent":3,"parameters":[]},{"code":412,"indent":2,"parameters":[]},{"code":0,"indent":2,"parameters":[]},{"code":412,"indent":1,"parameters":[]},{"code":0,"indent":1,"parameters":[]},{"code":412,"indent":0,"parameters":[]},{"code":230,"indent":0,"parameters":[30]},{"code":121,"indent":0,"parameters":[89,89,1]},{"code":0,"indent":0,"parameters":[]}],"span":0}]},
{"id":12,"members":[{"enemyId":14,"x":424,"y":444,"hidden":false}],"name":"Martha","pages":[{"conditions":{"actorHp":50,"actorId":1,"actorValid":false,"enemyHp":5,"enemyIndex":0,"enemyValid":true,"switchId":1,"switchValid":false,"turnA":0,"turnB":0,"turnEnding":false,"turnValid":false},"list":[{"code":331,"indent":0,"parameters":[-1,1,0,9999,true]},{"code":223,"indent":0,"parameters":[[0,0,0,0],60,false]},{"code":121,"indent":0,"parameters":[89,89,1]},{"code":250,"indent":0,"parameters":[{"name":"SE_Screamer2 (1)","volume":100,"pitch":120,"pan":0}]},{"code":0,"indent":0,"parameters":[]}],"span":0},{"conditions":{"actorHp":50,"actorId":1,"actorValid":false,"enemyHp":50,"enemyIndex":0,"enemyValid":false,"switchId":1,"switchValid":false,"turnA":0,"turnB":0,"turnEnding":false,"turnValid":true},"list":[{"code":117,"indent":0,"parameters":[412]},{"code":0,"indent":0,"parameters":[]}],"span":0},{"conditions":{"actorHp":50,"actorId":1,"actorValid":false,"enemyHp":50,"enemyIndex":0,"enemyValid":false,"switchId":89,"switchValid":true,"turnA":0,"turnB":0,"turnEnding":false,"turnValid":false},"list":[{"code":111,"indent":0,"parameters":[1,2,0,1,0]},{"code":339,"indent":1,"parameters":[1,1,1,-1]},{"code":0,"indent":1,"parameters":[]},{"code":411,"indent":0,"parameters":[]},{"code":111,"indent":1,"parameters":[1,2,0,2,0]},{"code":339,"indent":2,"parameters":[1,2,1,-1]},{"code":0,"indent":2,"parameters":[]},{"code":411,"indent":1,"parameters":[]},{"code":111,"indent":2,"parameters":[1,2,0,5,0]},{"code":339,"indent":3,"parameters":[1,5,1,-1]},{"code":0,"indent":3,"parameters":[]},{"code":411,"indent":2,"parameters":[]},{"code":111,"indent":3,"parameters":[1,2,0,6,0]},{"code":339,"indent":4,"parameters":[1,6,1,-1]},{"code":0,"indent":4,"parameters":[]},{"code":412,"indent":3,"parameters":[]},{"code":0,"indent":3,"parameters":[]},{"code":412,"indent":2,"parameters":[]},{"code":0,"indent":2,"parameters":[]},{"code":412,"indent":1,"parameters":[]},{"code":0,"indent":1,"parameters":[]},{"code":412,"indent":0,"parameters":[]},{"code":230,"indent":0,"parameters":[30]},{"code":121,"indent":0,"parameters":[89,89,1]},{"code":0,"indent":0,"parameters":[]}],"span":0}]},
{"id":13,"members":[{"enemyId":15,"x":430,"y":444,"hidden":false}],"name":"GhostOfThePast","pages":[{"conditions":{"actorHp":50,"actorId":1,"actorValid":false,"enemyHp":5,"enemyIndex":0,"enemyValid":true,"switchId":1,"switchValid":false,"turnA":0,"turnB":0,"turnEnding":false,"turnValid":false},"list":[{"code":331,"indent":0,"parameters":[-1,1,0,9999,true]},{"code":223,"indent":0,"parameters":[[0,0,0,0],60,false]},{"code":121,"indent":0,"parameters":[89,89,1]},{"code":250,"indent":0,"parameters":[{"name":"SE_DeathEnemy","volume":100,"pitch":100,"pan":0}]},{"code":0,"indent":0,"parameters":[]}],"span":0},{"conditions":{"actorHp":50,"actorId":1,"actorValid":false,"enemyHp":50,"enemyIndex":0,"enemyValid":false,"switchId":89,"switchValid":true,"turnA":0,"turnB":0,"turnEnding":false,"turnValid":false},"list":[{"code":111,"indent":0,"parameters":[1,2,0,1,0]},{"code":339,"indent":1,"parameters":[1,1,1,-1]},{"code":0,"indent":1,"parameters":[]},{"code":411,"indent":0,"parameters":[]},{"code":111,"indent":1,"parameters":[1,2,0,2,0]},{"code":339,"indent":2,"parameters":[1,2,1,-1]},{"code":0,"indent":2,"parameters":[]},{"code":411,"indent":1,"parameters":[]},{"code":111,"indent":2,"parameters":[1,2,0,5,0]},{"code":339,"indent":3,"parameters":[1,5,1,-1]},{"code":0,"indent":3,"parameters":[]},{"code":411,"indent":2,"parameters":[]},{"code":111,"indent":3,"parameters":[1,2,0,6,0]},{"code":339,"indent":4,"parameters":[1,6,1,-1]},{"code":0,"indent":4,"parameters":[]},{"code":412,"indent":3,"parameters":[]},{"code":0,"indent":3,"parameters":[]},{"code":412,"indent":2,"parameters":[]},{"code":0,"indent":2,"parameters":[]},{"code":412,"indent":1,"parameters":[]},{"code":0,"indent":1,"parameters":[]},{"code":412,"indent":0,"parameters":[]},{"code":230,"indent":0,"parameters":[30]},{"code":121,"indent":0,"parameters":[89,89,1]},{"code":0,"indent":0,"parameters":[]}],"span":0}]},
{"id":14,"members":[{"enemyId":18,"x":298,"y":306,"hidden":false}],"name":"Dog 1","pages":[{"conditions":{"actorHp":1,"actorId":8,"actorValid":false,"enemyHp":50,"enemyIndex":0,"enemyValid":false,"switchId":1,"switchValid":false,"turnA":0,"turnB":0,"turnEnding":false,"turnValid":true},"list":[{"code":111,"indent":0,"parameters":[0,77,0]},{"code":0,"indent":1,"parameters":[]},{"code":411,"indent":0,"parameters":[]},{"code":101,"indent":1,"parameters":["",0,1,1]},{"code":401,"indent":1,"parameters":["\\c[1]{EnemyEncounter18}"]},{"code":121,"indent":1,"parameters":[77,77,0]},{"code":224,"indent":1,"parameters":[[255,0,0,187],200,false]},{"code":0,"indent":1,"parameters":[]},{"code":412,"indent":0,"parameters":[]},{"code":0,"indent":0,"parameters":[]}],"span":0},{"conditions":{"actorHp":50,"actorId":1,"actorValid":false,"enemyHp":5,"enemyIndex":0,"enemyValid":true,"switchId":1,"switchValid":false,"turnA":0,"turnB":0,"turnEnding":false,"turnValid":false},"list":[{"code":331,"indent":0,"parameters":[-1,1,0,9999,true]},{"code":223,"indent":0,"parameters":[[0,0,0,0],60,false]},{"code":121,"indent":0,"parameters":[89,89,1]},{"code":250,"indent":0,"parameters":[{"name":"SE_Dog7","volume":100,"pitch":100,"pan":0}]},{"code":0,"indent":0,"parameters":[]}],"span":0},{"conditions":{"actorHp":50,"actorId":1,"actorValid":false,"enemyHp":50,"enemyIndex":0,"enemyValid":false,"switchId":89,"switchValid":true,"turnA":0,"turnB":0,"turnEnding":false,"turnValid":false},"list":[{"code":111,"indent":0,"parameters":[1,2,0,1,0]},{"code":339,"indent":1,"parameters":[1,1,1,-1]},{"code":0,"indent":1,"parameters":[]},{"code":411,"indent":0,"parameters":[]},{"code":111,"indent":1,"parameters":[1,2,0,2,0]},{"code":339,"indent":2,"parameters":[1,2,1,-1]},{"code":0,"indent":2,"parameters":[]},{"code":411,"indent":1,"parameters":[]},{"code":111,"indent":2,"parameters":[1,2,0,5,0]},{"code":339,"indent":3,"parameters":[1,5,1,-1]},{"code":0,"indent":3,"parameters":[]},{"code":411,"indent":2,"parameters":[]},{"code":111,"indent":3,"parameters":[1,2,0,6,0]},{"code":339,"indent":4,"parameters":[1,6,1,-1]},{"code":0,"indent":4,"parameters":[]},{"code":412,"indent":3,"parameters":[]},{"code":0,"indent":3,"parameters":[]},{"code":412,"indent":2,"parameters":[]},{"code":0,"indent":2,"parameters":[]},{"code":412,"indent":1,"parameters":[]},{"code":0,"indent":1,"parameters":[]},{"code":412,"indent":0,"parameters":[]},{"code":230,"indent":0,"parameters":[30]},{"code":121,"indent":0,"parameters":[89,89,1]},{"code":0,"indent":0,"parameters":[]}],"span":0},{"conditions":{"actorHp":50,"actorId":1,"actorValid":false,"enemyHp":50,"enemyIndex":0,"enemyValid":false,"switchId":57,"switchValid":true,"turnA":0,"turnB":0,"turnEnding":false,"turnValid":true},"list":[{"code":250,"indent":0,"parameters":[{"name":"SE_Success","volume":100,"pitch":100,"pan":0}]},{"code":313,"indent":0,"parameters":[1,2,0,27]},{"code":101,"indent":0,"parameters":["",0,1,1]},{"code":401,"indent":0,"parameters":["\\c[3]{SkillPerk17}<br>\\c[0]{D_SkillPerk17}"]},{"code":0,"indent":0,"parameters":[]}],"span":0}]},
{"id":15,"members":[{"enemyId":18,"x":298,"y":306,"hidden":false},{"enemyId":18,"x":741,"y":316,"hidden":false}],"name":"Dog 2","pages":[{"conditions":{"actorHp":50,"actorId":1,"actorValid":false,"enemyHp":5,"enemyIndex":0,"enemyValid":true,"switchId":1,"switchValid":false,"turnA":0,"turnB":0,"turnEnding":false,"turnValid":false},"list":[{"code":223,"indent":0,"parameters":[[0,0,0,0],60,false]},{"code":121,"indent":0,"parameters":[89,89,1]},{"code":121,"indent":0,"parameters":[381,381,1]},{"code":250,"indent":0,"parameters":[{"name":"SE_Dog7","volume":100,"pitch":100,"pan":0}]},{"code":0,"indent":0,"parameters":[]}],"span":0},{"conditions":{"actorHp":50,"actorId":1,"actorValid":false,"enemyHp":5,"enemyIndex":1,"enemyValid":true,"switchId":1,"switchValid":false,"turnA":0,"turnB":0,"turnEnding":false,"turnValid":false},"list":[{"code":223,"indent":0,"parameters":[[0,0,0,0],60,false]},{"code":121,"indent":0,"parameters":[89,89,1]},{"code":121,"indent":0,"parameters":[381,381,1]},{"code":250,"indent":0,"parameters":[{"name":"SE_Dog7","volume":100,"pitch":100,"pan":0}]},{"code":0,"indent":0,"parameters":[]}],"span":0},{"conditions":{"actorHp":50,"actorId":1,"actorValid":false,"enemyHp":50,"enemyIndex":0,"enemyValid":false,"switchId":89,"switchValid":true,"turnA":0,"turnB":0,"turnEnding":false,"turnValid":false},"list":[{"code":111,"indent":0,"parameters":[1,2,0,1,0]},{"code":339,"indent":1,"parameters":[1,1,1,-1]},{"code":0,"indent":1,"parameters":[]},{"code":411,"indent":0,"parameters":[]},{"code":111,"indent":1,"parameters":[1,2,0,2,0]},{"code":339,"indent":2,"parameters":[1,2,1,-1]},{"code":0,"indent":2,"parameters":[]},{"code":411,"indent":1,"parameters":[]},{"code":111,"indent":2,"parameters":[1,2,0,5,0]},{"code":339,"indent":3,"parameters":[1,5,1,-1]},{"code":0,"indent":3,"parameters":[]},{"code":411,"indent":2,"parameters":[]},{"code":111,"indent":3,"parameters":[1,2,0,6,0]},{"code":339,"indent":4,"parameters":[1,6,1,-1]},{"code":0,"indent":4,"parameters":[]},{"code":412,"indent":3,"parameters":[]},{"code":0,"indent":3,"parameters":[]},{"code":412,"indent":2,"parameters":[]},{"code":0,"indent":2,"parameters":[]},{"code":412,"indent":1,"parameters":[]},{"code":0,"indent":1,"parameters":[]},{"code":412,"indent":0,"parameters":[]},{"code":230,"indent":0,"parameters":[30]},{"code":121,"indent":0,"parameters":[89,89,1]},{"code":0,"indent":0,"parameters":[]}],"span":0},{"conditions":{"actorHp":50,"actorId":1,"actorValid":false,"enemyHp":50,"enemyIndex":0,"enemyValid":false,"switchId":57,"switchValid":true,"turnA":0,"turnB":0,"turnEnding":false,"turnValid":true},"list":[{"code":250,"indent":0,"parameters":[{"name":"SE_Success","volume":100,"pitch":100,"pan":0}]},{"code":313,"indent":0,"parameters":[1,2,0,27]},{"code":101,"indent":0,"parameters":["",0,1,1]},{"code":401,"indent":0,"parameters":["\\c[3]{SkillPerk17}<br>\\c[0]{D_SkillPerk17}"]},{"code":0,"indent":0,"parameters":[]}],"span":0},{"conditions":{"actorHp":50,"actorId":1,"actorValid":false,"enemyHp":50,"enemyIndex":0,"enemyValid":false,"switchId":1,"switchValid":false,"turnA":0,"turnB":0,"turnEnding":false,"turnValid":true},"list":[{"code":111,"indent":0,"parameters":[0,381,1]},{"code":121,"indent":1,"parameters":[381,381,0]},{"code":333,"indent":1,"parameters":[-1,0,63]},{"code":101,"indent":1,"parameters":["",0,1,1]},{"code":401,"indent":1,"parameters":["\\c[1]{PackOfDogs}<br>\\c[0]{Stat_STR_rise2}"]},{"code":0,"indent":1,"parameters":[]},{"code":412,"indent":0,"parameters":[]},{"code":0,"indent":0,"parameters":[]}],"span":0},{"conditions":{"actorHp":50,"actorId":1,"actorValid":false,"enemyHp":50,"enemyIndex":0,"enemyValid":false,"switchId":1,"switchValid":false,"turnA":0,"turnB":0,"turnEnding":true,"turnValid":false},"list":[{"code":108,"indent":0,"parameters":["Enemy - STR_Rise status"]},{"code":111,"indent":0,"parameters":[5,0,1,1]},{"code":122,"indent":1,"parameters":[72,72,1,0,1]},{"code":0,"indent":1,"parameters":[]},{"code":412,"indent":0,"parameters":[]},{"code":111,"indent":0,"parameters":[5,1,1,1]},{"code":122,"indent":1,"parameters":[72,72,1,0,1]},{"code":0,"indent":1,"parameters":[]},{"code":412,"indent":0,"parameters":[]},{"code":111,"indent":0,"parameters":[1,72,0,1,1]},{"code":333,"indent":1,"parameters":[-1,1,63]},{"code":333,"indent":1,"parameters":[-1,1,64]},{"code":0,"indent":1,"parameters":[]},{"code":411,"indent":0,"parameters":[]},{"code":0,"indent":1,"parameters":[]},{"code":412,"indent":0,"parameters":[]},{"code":122,"indent":0,"parameters":[72,72,0,0,0]},{"code":0,"indent":0,"parameters":[]}],"span":1}]},
{"id":16,"members":[{"enemyId":18,"x":418,"y":315,"hidden":false},{"enemyId":18,"x":816,"y":265,"hidden":false},{"enemyId":18,"x":96,"y":307,"hidden":false}],"name":"Dog 3","pages":[{"conditions":{"actorHp":50,"actorId":1,"actorValid":false,"enemyHp":5,"enemyIndex":0,"enemyValid":true,"switchId":1,"switchValid":false,"turnA":0,"turnB":0,"turnEnding":false,"turnValid":false},"list":[{"code":223,"indent":0,"parameters":[[0,0,0,0],60,false]},{"code":121,"indent":0,"parameters":[89,89,1]},{"code":121,"indent":0,"parameters":[381,381,1]},{"code":250,"indent":0,"parameters":[{"name":"SE_Dog7","volume":100,"pitch":100,"pan":0}]},{"code":0,"indent":0,"parameters":[]}],"span":0},{"conditions":{"actorHp":50,"actorId":1,"actorValid":false,"enemyHp":5,"enemyIndex":1,"enemyValid":true,"switchId":1,"switchValid":false,"turnA":0,"turnB":0,"turnEnding":false,"turnValid":false},"list":[{"code":223,"indent":0,"parameters":[[0,0,0,0],60,false]},{"code":121,"indent":0,"parameters":[89,89,1]},{"code":121,"indent":0,"parameters":[381,381,1]},{"code":250,"indent":0,"parameters":[{"name":"SE_Dog7","volume":100,"pitch":100,"pan":0}]},{"code":0,"indent":0,"parameters":[]}],"span":0},{"conditions":{"actorHp":50,"actorId":1,"actorValid":false,"enemyHp":5,"enemyIndex":2,"enemyValid":true,"switchId":1,"switchValid":false,"turnA":0,"turnB":0,"turnEnding":false,"turnValid":false},"list":[{"code":223,"indent":0,"parameters":[[0,0,0,0],60,false]},{"code":121,"indent":0,"parameters":[89,89,1]},{"code":121,"indent":0,"parameters":[381,381,1]},{"code":250,"indent":0,"parameters":[{"name":"SE_Dog7","volume":100,"pitch":100,"pan":0}]},{"code":0,"indent":0,"parameters":[]}],"span":0},{"conditions":{"actorHp":50,"actorId":1,"actorValid":false,"enemyHp":50,"enemyIndex":0,"enemyValid":false,"switchId":89,"switchValid":true,"turnA":0,"turnB":0,"turnEnding":false,"turnValid":false},"list":[{"code":111,"indent":0,"parameters":[1,2,0,1,0]},{"code":339,"indent":1,"parameters":[1,1,1,-1]},{"code":0,"indent":1,"parameters":[]},{"code":411,"indent":0,"parameters":[]},{"code":111,"indent":1,"parameters":[1,2,0,2,0]},{"code":339,"indent":2,"parameters":[1,2,1,-1]},{"code":0,"indent":2,"parameters":[]},{"code":411,"indent":1,"parameters":[]},{"code":111,"indent":2,"parameters":[1,2,0,5,0]},{"code":339,"indent":3,"parameters":[1,5,1,-1]},{"code":0,"indent":3,"parameters":[]},{"code":411,"indent":2,"parameters":[]},{"code":111,"indent":3,"parameters":[1,2,0,6,0]},{"code":339,"indent":4,"parameters":[1,6,1,-1]},{"code":0,"indent":4,"parameters":[]},{"code":412,"indent":3,"parameters":[]},{"code":0,"indent":3,"parameters":[]},{"code":412,"indent":2,"parameters":[]},{"code":0,"indent":2,"parameters":[]},{"code":412,"indent":1,"parameters":[]},{"code":0,"indent":1,"parameters":[]},{"code":412,"indent":0,"parameters":[]},{"code":230,"indent":0,"parameters":[30]},{"code":121,"indent":0,"parameters":[89,89,1]},{"code":0,"indent":0,"parameters":[]}],"span":0},{"conditions":{"actorHp":50,"actorId":1,"actorValid":false,"enemyHp":50,"enemyIndex":0,"enemyValid":false,"switchId":57,"switchValid":true,"turnA":0,"turnB":0,"turnEnding":false,"turnValid":true},"list":[{"code":250,"indent":0,"parameters":[{"name":"SE_Success","volume":100,"pitch":100,"pan":0}]},{"code":313,"indent":0,"parameters":[1,2,0,27]},{"code":101,"indent":0,"parameters":["",0,1,1]},{"code":401,"indent":0,"parameters":["\\c[3]{SkillPerk17}<br>\\c[0]{D_SkillPerk17}"]},{"code":0,"indent":0,"parameters":[]}],"span":0},{"conditions":{"actorHp":50,"actorId":1,"actorValid":false,"enemyHp":50,"enemyIndex":0,"enemyValid":false,"switchId":1,"switchValid":false,"turnA":0,"turnB":0,"turnEnding":false,"turnValid":true},"list":[{"code":111,"indent":0,"parameters":[0,381,1]},{"code":121,"indent":1,"parameters":[381,381,0]},{"code":313,"indent":1,"parameters":[0,0,0,62]},{"code":333,"indent":1,"parameters":[-1,0,64]},{"code":101,"indent":1,"parameters":["",0,1,1]},{"code":401,"indent":1,"parameters":["\\c[1]{PackOfDogs}<br>\\c[0]{Stat_STR_rise2}"]},{"code":101,"indent":1,"parameters":["",0,1,1]},{"code":401,"indent":1,"parameters":["\\c[1]{Surrounded}<br>\\c[0]{Stat_SAN_Lost2}"]},{"code":0,"indent":1,"parameters":[]},{"code":412,"indent":0,"parameters":[]},{"code":0,"indent":0,"parameters":[]}],"span":0},{"conditions":{"actorHp":50,"actorId":1,"actorValid":false,"enemyHp":50,"enemyIndex":0,"enemyValid":false,"switchId":1,"switchValid":false,"turnA":0,"turnB":0,"turnEnding":true,"turnValid":false},"list":[{"code":108,"indent":0,"parameters":["Actor - San_Lost status"]},{"code":111,"indent":0,"parameters":[5,0,1,1]},{"code":122,"indent":1,"parameters":[72,72,1,0,1]},{"code":0,"indent":1,"parameters":[]},{"code":412,"indent":0,"parameters":[]},{"code":111,"indent":0,"parameters":[5,1,1,1]},{"code":122,"indent":1,"parameters":[72,72,1,0,1]},{"code":0,"indent":1,"parameters":[]},{"code":412,"indent":0,"parameters":[]},{"code":111,"indent":0,"parameters":[5,2,1,1]},{"code":122,"indent":1,"parameters":[72,72,1,0,1]},{"code":0,"indent":1,"parameters":[]},{"code":412,"indent":0,"parameters":[]},{"code":111,"indent":0,"parameters":[1,72,0,2,1]},{"code":313,"indent":1,"parameters":[0,0,1,62]},{"code":333,"indent":1,"parameters":[-1,1,63]},{"code":333,"indent":1,"parameters":[-1,1,64]},{"code":0,"indent":1,"parameters":[]},{"code":411,"indent":0,"parameters":[]},{"code":0,"indent":1,"parameters":[]},{"code":412,"indent":0,"parameters":[]},{"code":122,"indent":0,"parameters":[72,72,0,0,0]},{"code":0,"indent":0,"parameters":[]}],"span":1}]},
{"id":17,"members":[{"enemyId":19,"x":490,"y":336,"hidden":false}],"name":"Wolf 1","pages":[{"conditions":{"actorHp":1,"actorId":8,"actorValid":false,"enemyHp":50,"enemyIndex":0,"enemyValid":false,"switchId":1,"switchValid":false,"turnA":0,"turnB":0,"turnEnding":false,"turnValid":true},"list":[{"code":111,"indent":0,"parameters":[0,78,0]},{"code":0,"indent":1,"parameters":[]},{"code":411,"indent":0,"parameters":[]},{"code":101,"indent":1,"parameters":["",0,1,1]},{"code":401,"indent":1,"parameters":["\\c[1]{EnemyEncounter19}"]},{"code":121,"indent":1,"parameters":[78,78,0]},{"code":224,"indent":1,"parameters":[[255,0,0,187],200,false]},{"code":0,"indent":1,"parameters":[]},{"code":412,"indent":0,"parameters":[]},{"code":0,"indent":0,"parameters":[]}],"span":0},{"conditions":{"actorHp":50,"actorId":1,"actorValid":false,"enemyHp":5,"enemyIndex":0,"enemyValid":true,"switchId":1,"switchValid":false,"turnA":0,"turnB":0,"turnEnding":false,"turnValid":false},"list":[{"code":331,"indent":0,"parameters":[-1,1,0,9999,true]},{"code":223,"indent":0,"parameters":[[0,0,0,0],60,false]},{"code":121,"indent":0,"parameters":[89,89,1]},{"code":121,"indent":0,"parameters":[381,381,1]},{"code":250,"indent":0,"parameters":[{"name":"SE_Dog7","volume":100,"pitch":100,"pan":0}]},{"code":0,"indent":0,"parameters":[]}],"span":0},{"conditions":{"actorHp":50,"actorId":1,"actorValid":false,"enemyHp":50,"enemyIndex":0,"enemyValid":false,"switchId":89,"switchValid":true,"turnA":0,"turnB":0,"turnEnding":false,"turnValid":false},"list":[{"code":111,"indent":0,"parameters":[1,2,0,1,0]},{"code":339,"indent":1,"parameters":[1,1,1,-1]},{"code":0,"indent":1,"parameters":[]},{"code":411,"indent":0,"parameters":[]},{"code":111,"indent":1,"parameters":[1,2,0,2,0]},{"code":339,"indent":2,"parameters":[1,2,1,-1]},{"code":0,"indent":2,"parameters":[]},{"code":411,"indent":1,"parameters":[]},{"code":111,"indent":2,"parameters":[1,2,0,5,0]},{"code":339,"indent":3,"parameters":[1,5,1,-1]},{"code":0,"indent":3,"parameters":[]},{"code":411,"indent":2,"parameters":[]},{"code":111,"indent":3,"parameters":[1,2,0,6,0]},{"code":339,"indent":4,"parameters":[1,6,1,-1]},{"code":0,"indent":4,"parameters":[]},{"code":412,"indent":3,"parameters":[]},{"code":0,"indent":3,"parameters":[]},{"code":412,"indent":2,"parameters":[]},{"code":0,"indent":2,"parameters":[]},{"code":412,"indent":1,"parameters":[]},{"code":0,"indent":1,"parameters":[]},{"code":412,"indent":0,"parameters":[]},{"code":230,"indent":0,"parameters":[30]},{"code":121,"indent":0,"parameters":[89,89,1]},{"code":0,"indent":0,"parameters":[]}],"span":0},{"conditions":{"actorHp":50,"actorId":1,"actorValid":false,"enemyHp":50,"enemyIndex":0,"enemyValid":false,"switchId":57,"switchValid":true,"turnA":0,"turnB":0,"turnEnding":false,"turnValid":true},"list":[{"code":250,"indent":0,"parameters":[{"name":"SE_Success","volume":100,"pitch":100,"pan":0}]},{"code":313,"indent":0,"parameters":[1,2,0,27]},{"code":101,"indent":0,"parameters":["",0,1,1]},{"code":401,"indent":0,"parameters":["\\c[3]{SkillPerk17}<br>\\c[0]{D_SkillPerk17}"]},{"code":0,"indent":0,"parameters":[]}],"span":0}]},
{"id":18,"members":[{"enemyId":19,"x":145,"y":357,"hidden":false},{"enemyId":19,"x":621,"y":385,"hidden":false}],"name":"Wolf 2","pages":[{"conditions":{"actorHp":50,"actorId":1,"actorValid":false,"enemyHp":5,"enemyIndex":0,"enemyValid":true,"switchId":1,"switchValid":false,"turnA":0,"turnB":0,"turnEnding":false,"turnValid":false},"list":[{"code":223,"indent":0,"parameters":[[0,0,0,0],60,false]},{"code":121,"indent":0,"parameters":[89,89,1]},{"code":121,"indent":0,"parameters":[381,381,1]},{"code":250,"indent":0,"parameters":[{"name":"SE_Dog7","volume":100,"pitch":100,"pan":0}]},{"code":0,"indent":0,"parameters":[]}],"span":0},{"conditions":{"actorHp":50,"actorId":1,"actorValid":false,"enemyHp":5,"enemyIndex":1,"enemyValid":true,"switchId":1,"switchValid":false,"turnA":0,"turnB":0,"turnEnding":false,"turnValid":false},"list":[{"code":223,"indent":0,"parameters":[[0,0,0,0],60,false]},{"code":121,"indent":0,"parameters":[89,89,1]},{"code":121,"indent":0,"parameters":[381,381,1]},{"code":250,"indent":0,"parameters":[{"name":"SE_Dog7","volume":100,"pitch":100,"pan":0}]},{"code":0,"indent":0,"parameters":[]}],"span":0},{"conditions":{"actorHp":50,"actorId":1,"actorValid":false,"enemyHp":50,"enemyIndex":0,"enemyValid":false,"switchId":89,"switchValid":true,"turnA":0,"turnB":0,"turnEnding":false,"turnValid":false},"list":[{"code":111,"indent":0,"parameters":[1,2,0,1,0]},{"code":339,"indent":1,"parameters":[1,1,1,-1]},{"code":0,"indent":1,"parameters":[]},{"code":411,"indent":0,"parameters":[]},{"code":111,"indent":1,"parameters":[1,2,0,2,0]},{"code":339,"indent":2,"parameters":[1,2,1,-1]},{"code":0,"indent":2,"parameters":[]},{"code":411,"indent":1,"parameters":[]},{"code":111,"indent":2,"parameters":[1,2,0,5,0]},{"code":339,"indent":3,"parameters":[1,5,1,-1]},{"code":0,"indent":3,"parameters":[]},{"code":411,"indent":2,"parameters":[]},{"code":111,"indent":3,"parameters":[1,2,0,6,0]},{"code":339,"indent":4,"parameters":[1,6,1,-1]},{"code":0,"indent":4,"parameters":[]},{"code":412,"indent":3,"parameters":[]},{"code":0,"indent":3,"parameters":[]},{"code":412,"indent":2,"parameters":[]},{"code":0,"indent":2,"parameters":[]},{"code":412,"indent":1,"parameters":[]},{"code":0,"indent":1,"parameters":[]},{"code":412,"indent":0,"parameters":[]},{"code":230,"indent":0,"parameters":[30]},{"code":121,"indent":0,"parameters":[89,89,1]},{"code":0,"indent":0,"parameters":[]}],"span":0},{"conditions":{"actorHp":50,"actorId":1,"actorValid":false,"enemyHp":50,"enemyIndex":0,"enemyValid":false,"switchId":57,"switchValid":true,"turnA":0,"turnB":0,"turnEnding":false,"turnValid":true},"list":[{"code":250,"indent":0,"parameters":[{"name":"SE_Success","volume":100,"pitch":100,"pan":0}]},{"code":313,"indent":0,"parameters":[1,2,0,27]},{"code":101,"indent":0,"parameters":["",0,1,1]},{"code":401,"indent":0,"parameters":["\\c[3]{SkillPerk17}<br>\\c[0]{D_SkillPerk17}"]},{"code":0,"indent":0,"parameters":[]}],"span":0},{"conditions":{"actorHp":50,"actorId":1,"actorValid":false,"enemyHp":50,"enemyIndex":0,"enemyValid":false,"switchId":1,"switchValid":false,"turnA":0,"turnB":0,"turnEnding":false,"turnValid":true},"list":[{"code":111,"indent":0,"parameters":[0,381,1]},{"code":121,"indent":1,"parameters":[381,381,0]},{"code":313,"indent":1,"parameters":[0,0,0,62]},{"code":333,"indent":1,"parameters":[-1,0,64]},{"code":101,"indent":1,"parameters":["",0,1,1]},{"code":401,"indent":1,"parameters":["\\c[1]{PackOfDogs}<br>\\c[0]{Stat_STR_rise2}"]},{"code":101,"indent":1,"parameters":["",0,1,1]},{"code":401,"indent":1,"parameters":["\\c[1]{Surrounded}<br>\\c[0]{Stat_SAN_Lost2}"]},{"code":0,"indent":1,"parameters":[]},{"code":412,"indent":0,"parameters":[]},{"code":0,"indent":0,"parameters":[]}],"span":0},{"conditions":{"actorHp":50,"actorId":1,"actorValid":false,"enemyHp":50,"enemyIndex":0,"enemyValid":false,"switchId":1,"switchValid":false,"turnA":0,"turnB":0,"turnEnding":true,"turnValid":false},"list":[{"code":108,"indent":0,"parameters":["Actor - San_Lost status"]},{"code":111,"indent":0,"parameters":[5,0,1,1]},{"code":122,"indent":1,"parameters":[72,72,1,0,1]},{"code":0,"indent":1,"parameters":[]},{"code":412,"indent":0,"parameters":[]},{"code":111,"indent":0,"parameters":[5,1,1,1]},{"code":122,"indent":1,"parameters":[72,72,1,0,1]},{"code":0,"indent":1,"parameters":[]},{"code":412,"indent":0,"parameters":[]},{"code":111,"indent":0,"parameters":[1,72,0,1,1]},{"code":313,"indent":1,"parameters":[0,0,1,62]},{"code":333,"indent":1,"parameters":[-1,1,63]},{"code":333,"indent":1,"parameters":[-1,1,64]},{"code":0,"indent":1,"parameters":[]},{"code":411,"indent":0,"parameters":[]},{"code":0,"indent":1,"parameters":[]},{"code":412,"indent":0,"parameters":[]},{"code":122,"indent":0,"parameters":[72,72,0,0,0]},{"code":0,"indent":0,"parameters":[]}],"span":1}]},
{"id":19,"members":[{"enemyId":20,"x":477,"y":444,"hidden":false},{"enemyId":18,"x":0,"y":334,"hidden":true},{"enemyId":18,"x":744,"y":313,"hidden":true}],"name":"Pit bull","pages":[{"conditions":{"actorHp":1,"actorId":8,"actorValid":false,"enemyHp":50,"enemyIndex":0,"enemyValid":false,"switchId":1,"switchValid":false,"turnA":0,"turnB":0,"turnEnding":false,"turnValid":true},"list":[{"code":111,"indent":0,"parameters":[0,79,0]},{"code":0,"indent":1,"parameters":[]},{"code":411,"indent":0,"parameters":[]},{"code":101,"indent":1,"parameters":["",0,1,1]},{"code":401,"indent":1,"parameters":["\\c[1]{EnemyEncounter20}"]},{"code":121,"indent":1,"parameters":[79,79,0]},{"code":224,"indent":1,"parameters":[[255,0,0,187],200,false]},{"code":0,"indent":1,"parameters":[]},{"code":412,"indent":0,"parameters":[]},{"code":121,"indent":0,"parameters":[383,383,0]},{"code":0,"indent":0,"parameters":[]}],"span":0},{"conditions":{"actorHp":50,"actorId":1,"actorValid":false,"enemyHp":5,"enemyIndex":0,"enemyValid":true,"switchId":1,"switchValid":false,"turnA":0,"turnB":0,"turnEnding":false,"turnValid":false},"list":[{"code":331,"indent":0,"parameters":[-1,1,0,9999,true]},{"code":223,"indent":0,"parameters":[[0,0,0,0],60,false]},{"code":121,"indent":0,"parameters":[89,89,1]},{"code":121,"indent":0,"parameters":[381,381,1]},{"code":250,"indent":0,"parameters":[{"name":"SE_Dog7","volume":100,"pitch":100,"pan":0}]},{"code":0,"indent":0,"parameters":[]}],"span":0},{"conditions":{"actorHp":50,"actorId":1,"actorValid":false,"enemyHp":50,"enemyIndex":0,"enemyValid":false,"switchId":57,"switchValid":true,"turnA":0,"turnB":0,"turnEnding":false,"turnValid":true},"list":[{"code":250,"indent":0,"parameters":[{"name":"SE_Success","volume":100,"pitch":100,"pan":0}]},{"code":313,"indent":0,"parameters":[1,2,0,27]},{"code":101,"indent":0,"parameters":["",0,1,1]},{"code":401,"indent":0,"parameters":["\\c[3]{SkillPerk17}<br>\\c[0]{D_SkillPerk17}"]},{"code":0,"indent":0,"parameters":[]}],"span":0},{"conditions":{"actorHp":50,"actorId":1,"actorValid":false,"enemyHp":50,"enemyIndex":0,"enemyValid":false,"switchId":89,"switchValid":true,"turnA":0,"turnB":0,"turnEnding":false,"turnValid":false},"list":[{"code":111,"indent":0,"parameters":[1,2,0,1,0]},{"code":339,"indent":1,"parameters":[1,1,1,-1]},{"code":0,"indent":1,"parameters":[]},{"code":411,"indent":0,"parameters":[]},{"code":111,"indent":1,"parameters":[1,2,0,2,0]},{"code":339,"indent":2,"parameters":[1,2,1,-1]},{"code":0,"indent":2,"parameters":[]},{"code":411,"indent":1,"parameters":[]},{"code":111,"indent":2,"parameters":[1,2,0,5,0]},{"code":339,"indent":3,"parameters":[1,5,1,-1]},{"code":0,"indent":3,"parameters":[]},{"code":411,"indent":2,"parameters":[]},{"code":111,"indent":3,"parameters":[1,2,0,6,0]},{"code":339,"indent":4,"parameters":[1,6,1,-1]},{"code":0,"indent":4,"parameters":[]},{"code":412,"indent":3,"parameters":[]},{"code":0,"indent":3,"parameters":[]},{"code":412,"indent":2,"parameters":[]},{"code":0,"indent":2,"parameters":[]},{"code":412,"indent":1,"parameters":[]},{"code":0,"indent":1,"parameters":[]},{"code":412,"indent":0,"parameters":[]},{"code":230,"indent":0,"parameters":[30]},{"code":121,"indent":0,"parameters":[89,89,1]},{"code":0,"indent":0,"parameters":[]}],"span":0},{"conditions":{"actorHp":50,"actorId":1,"actorValid":false,"enemyHp":50,"enemyIndex":0,"enemyValid":false,"switchId":88,"switchValid":true,"turnA":0,"turnB":0,"turnEnding":false,"turnValid":false},"list":[{"code":111,"indent":0,"parameters":[1,2,0,1,0]},{"code":339,"indent":1,"parameters":[1,1,49,-1]},{"code":0,"indent":1,"parameters":[]},{"code":411,"indent":0,"parameters":[]},{"code":111,"indent":1,"parameters":[1,2,0,2,0]},{"code":339,"indent":2,"parameters":[1,2,49,-1]},{"code":0,"indent":2,"parameters":[]},{"code":411,"indent":1,"parameters":[]},{"code":111,"indent":2,"parameters":[1,2,0,5,0]},{"code":339,"indent":3,"parameters":[1,5,49,-1]},{"code":0,"indent":3,"parameters":[]},{"code":411,"indent":2,"parameters":[]},{"code":111,"indent":3,"parameters":[1,2,0,6,0]},{"code":339,"indent":4,"parameters":[1,6,49,-1]},{"code":0,"indent":4,"parameters":[]},{"code":412,"indent":3,"parameters":[]},{"code":0,"indent":3,"parameters":[]},{"code":412,"indent":2,"parameters":[]},{"code":0,"indent":2,"parameters":[]},{"code":412,"indent":1,"parameters":[]},{"code":0,"indent":1,"parameters":[]},{"code":412,"indent":0,"parameters":[]},{"code":230,"indent":0,"parameters":[30]},{"code":121,"indent":0,"parameters":[88,88,1]},{"code":0,"indent":0,"parameters":[]}],"span":0},{"conditions":{"actorHp":50,"actorId":1,"actorValid":false,"enemyHp":50,"enemyIndex":0,"enemyValid":false,"switchId":382,"switchValid":true,"turnA":0,"turnB":0,"turnEnding":false,"turnValid":false},"list":[{"code":335,"indent":0,"parameters":[1]},{"code":335,"indent":0,"parameters":[2]},{"code":111,"indent":0,"parameters":[0,381,1]},{"code":121,"indent":1,"parameters":[381,381,0]},{"code":313,"indent":1,"parameters":[0,0,0,62]},{"code":333,"indent":1,"parameters":[-1,0,64]},{"code":101,"indent":1,"parameters":["",0,1,1]},{"code":401,"indent":1,"parameters":["\\c[1]{PackOfDogs}<br>\\c[0]{Stat_STR_rise2}"]},{"code":101,"indent":1,"parameters":["",0,1,1]},{"code":401,"indent":1,"parameters":["\\c[1]{Surrounded}<br>\\c[0]{Stat_SAN_Lost2}"]},{"code":0,"indent":1,"parameters":[]},{"code":412,"indent":0,"parameters":[]},{"code":0,"indent":0,"parameters":[]}],"span":0},{"conditions":{"actorHp":50,"actorId":1,"actorValid":false,"enemyHp":50,"enemyIndex":0,"enemyValid":false,"switchId":1,"switchValid":false,"turnA":0,"turnB":0,"turnEnding":true,"turnValid":false},"list":[{"code":108,"indent":0,"parameters":["Actor - San_Lost status"]},{"code":111,"indent":0,"parameters":[5,1,1,1]},{"code":122,"indent":1,"parameters":[72,72,1,0,1]},{"code":0,"indent":1,"parameters":[]},{"code":412,"indent":0,"parameters":[]},{"code":111,"indent":0,"parameters":[5,2,1,1]},{"code":122,"indent":1,"parameters":[72,72,1,0,1]},{"code":0,"indent":1,"parameters":[]},{"code":412,"indent":0,"parameters":[]},{"code":111,"indent":0,"parameters":[1,72,0,2,1]},{"code":313,"indent":1,"parameters":[0,0,1,62]},{"code":333,"indent":1,"parameters":[-1,1,63]},{"code":333,"indent":1,"parameters":[-1,1,64]},{"code":0,"indent":1,"parameters":[]},{"code":411,"indent":0,"parameters":[]},{"code":0,"indent":1,"parameters":[]},{"code":412,"indent":0,"parameters":[]},{"code":122,"indent":0,"parameters":[72,72,0,0,0]},{"code":0,"indent":0,"parameters":[]}],"span":1},{"conditions":{"actorHp":50,"actorId":1,"actorValid":false,"enemyHp":25,"enemyIndex":0,"enemyValid":true,"switchId":1,"switchValid":false,"turnA":0,"turnB":0,"turnEnding":false,"turnValid":false},"list":[{"code":333,"indent":0,"parameters":[0,0,65]},{"code":101,"indent":0,"parameters":["",0,1,1]},{"code":401,"indent":0,"parameters":["\\c[1]{DogsRage}<br>\\c[0]{DogsRage1}"]},{"code":0,"indent":0,"parameters":[]}],"span":0}]},
{"id":20,"members":[],"name":"","pages":[{"conditions":{"actorHp":50,"actorId":1,"actorValid":false,"enemyHp":50,"enemyIndex":0,"enemyValid":false,"switchId":1,"switchValid":false,"turnA":0,"turnB":0,"turnEnding":false,"turnValid":false},"list":[{"code":0,"indent":0,"parameters":[]}],"span":0}]},
{"id":21,"members":[],"name":"","pages":[{"conditions":{"actorHp":50,"actorId":1,"actorValid":false,"enemyHp":50,"enemyIndex":0,"enemyValid":false,"switchId":1,"switchValid":false,"turnA":0,"turnB":0,"turnEnding":false,"turnValid":false},"list":[{"code":0,"indent":0,"parameters":[]}],"span":0}]},
{"id":22,"members":[],"name":"","pages":[{"conditions":{"actorHp":50,"actorId":1,"actorValid":false,"enemyHp":50,"enemyIndex":0,"enemyValid":false,"switchId":1,"switchValid":false,"turnA":0,"turnB":0,"turnEnding":false,"turnValid":false},"list":[{"code":0,"indent":0,"parameters":[]}],"span":0}]},
{"id":23,"members":[],"name":"","pages":[{"conditions":{"actorHp":50,"actorId":1,"actorValid":false,"enemyHp":50,"enemyIndex":0,"enemyValid":false,"switchId":1,"switchValid":false,"turnA":0,"turnB":0,"turnEnding":false,"turnValid":false},"list":[{"code":0,"indent":0,"parameters":[]}],"span":0}]},
{"id":24,"members":[],"name":"","pages":[{"conditions":{"actorHp":50,"actorId":1,"actorValid":false,"enemyHp":50,"enemyIndex":0,"enemyValid":false,"switchId":1,"switchValid":false,"turnA":0,"turnB":0,"turnEnding":false,"turnValid":false},"list":[{"code":0,"indent":0,"parameters":[]}],"span":0}]},
{"id":25,"members":[],"name":"","pages":[{"conditions":{"actorHp":50,"actorId":1,"actorValid":false,"enemyHp":50,"enemyIndex":0,"enemyValid":false,"switchId":1,"switchValid":false,"turnA":0,"turnB":0,"turnEnding":false,"turnValid":false},"list":[{"code":0,"indent":0,"parameters":[]}],"span":0}]},
{"id":26,"members":[],"name":"","pages":[{"conditions":{"actorHp":50,"actorId":1,"actorValid":false,"enemyHp":50,"enemyIndex":0,"enemyValid":false,"switchId":1,"switchValid":false,"turnA":0,"turnB":0,"turnEnding":false,"turnValid":false},"list":[{"code":0,"indent":0,"parameters":[]}],"span":0}]},
{"id":27,"members":[],"name":"","pages":[{"conditions":{"actorHp":50,"actorId":1,"actorValid":false,"enemyHp":50,"enemyIndex":0,"enemyValid":false,"switchId":1,"switchValid":false,"turnA":0,"turnB":0,"turnEnding":false,"turnValid":false},"list":[{"code":0,"indent":0,"parameters":[]}],"span":0}]},
{"id":28,"members":[],"name":"","pages":[{"conditions":{"actorHp":50,"actorId":1,"actorValid":false,"enemyHp":50,"enemyIndex":0,"enemyValid":false,"switchId":1,"switchValid":false,"turnA":0,"turnB":0,"turnEnding":false,"turnValid":false},"list":[{"code":0,"indent":0,"parameters":[]}],"span":0}]},
{"id":29,"members":[],"name":"","pages":[{"conditions":{"actorHp":50,"actorId":1,"actorValid":false,"enemyHp":50,"enemyIndex":0,"enemyValid":false,"switchId":1,"switchValid":false,"turnA":0,"turnB":0,"turnEnding":false,"turnValid":false},"list":[{"code":0,"indent":0,"parameters":[]}],"span":0}]},
{"id":30,"members":[],"name":"","pages":[{"conditions":{"actorHp":50,"actorId":1,"actorValid":false,"enemyHp":50,"enemyIndex":0,"enemyValid":false,"switchId":1,"switchValid":false,"turnA":0,"turnB":0,"turnEnding":false,"turnValid":false},"list":[{"code":0,"indent":0,"parameters":[]}],"span":0}]},
{"id":31,"members":[],"name":"","pages":[{"conditions":{"actorHp":50,"actorId":1,"actorValid":false,"enemyHp":50,"enemyIndex":0,"enemyValid":false,"switchId":1,"switchValid":false,"turnA":0,"turnB":0,"turnEnding":false,"turnValid":false},"list":[{"code":0,"indent":0,"parameters":[]}],"span":0}]},
{"id":32,"members":[],"name":"","pages":[{"conditions":{"actorHp":50,"actorId":1,"actorValid":false,"enemyHp":50,"enemyIndex":0,"enemyValid":false,"switchId":1,"switchValid":false,"turnA":0,"turnB":0,"turnEnding":false,"turnValid":false},"list":[{"code":0,"indent":0,"parameters":[]}],"span":0}]},
{"id":33,"members":[],"name":"","pages":[{"conditions":{"actorHp":50,"actorId":1,"actorValid":false,"enemyHp":50,"enemyIndex":0,"enemyValid":false,"switchId":1,"switchValid":false,"turnA":0,"turnB":0,"turnEnding":false,"turnValid":false},"list":[{"code":0,"indent":0,"parameters":[]}],"span":0}]},
{"id":34,"members":[],"name":"","pages":[{"conditions":{"actorHp":50,"actorId":1,"actorValid":false,"enemyHp":50,"enemyIndex":0,"enemyValid":false,"switchId":1,"switchValid":false,"turnA":0,"turnB":0,"turnEnding":false,"turnValid":false},"list":[{"code":0,"indent":0,"parameters":[]}],"span":0}]},
{"id":35,"members":[],"name":"","pages":[{"conditions":{"actorHp":50,"actorId":1,"actorValid":false,"enemyHp":50,"enemyIndex":0,"enemyValid":false,"switchId":1,"switchValid":false,"turnA":0,"turnB":0,"turnEnding":false,"turnValid":false},"list":[{"code":0,"indent":0,"parameters":[]}],"span":0}]},
{"id":36,"members":[],"name":"","pages":[{"conditions":{"actorHp":50,"actorId":1,"actorValid":false,"enemyHp":50,"enemyIndex":0,"enemyValid":false,"switchId":1,"switchValid":false,"turnA":0,"turnB":0,"turnEnding":false,"turnValid":false},"list":[{"code":0,"indent":0,"parameters":[]}],"span":0}]},
{"id":37,"members":[],"name":"","pages":[{"conditions":{"actorHp":50,"actorId":1,"actorValid":false,"enemyHp":50,"enemyIndex":0,"enemyValid":false,"switchId":1,"switchValid":false,"turnA":0,"turnB":0,"turnEnding":false,"turnValid":false},"list":[{"code":0,"indent":0,"parameters":[]}],"span":0}]},
{"id":38,"members":[],"name":"","pages":[{"conditions":{"actorHp":50,"actorId":1,"actorValid":false,"enemyHp":50,"enemyIndex":0,"enemyValid":false,"switchId":1,"switchValid":false,"turnA":0,"turnB":0,"turnEnding":false,"turnValid":false},"list":[{"code":0,"indent":0,"parameters":[]}],"span":0}]},
{"id":39,"members":[],"name":"","pages":[{"conditions":{"actorHp":50,"actorId":1,"actorValid":false,"enemyHp":50,"enemyIndex":0,"enemyValid":false,"switchId":1,"switchValid":false,"turnA":0,"turnB":0,"turnEnding":false,"turnValid":false},"list":[{"code":0,"indent":0,"parameters":[]}],"span":0}]},
{"id":40,"members":[],"name":"","pages":[{"conditions":{"actorHp":50,"actorId":1,"actorValid":false,"enemyHp":50,"enemyIndex":0,"enemyValid":false,"switchId":1,"switchValid":false,"turnA":0,"turnB":0,"turnEnding":false,"turnValid":false},"list":[{"code":0,"indent":0,"parameters":[]}],"span":0}]},
{"id":41,"members":[],"name":"","pages":[{"conditions":{"actorHp":50,"actorId":1,"actorValid":false,"enemyHp":50,"enemyIndex":0,"enemyValid":false,"switchId":1,"switchValid":false,"turnA":0,"turnB":0,"turnEnding":false,"turnValid":false},"list":[{"code":0,"indent":0,"parameters":[]}],"span":0}]},
{"id":42,"members":[],"name":"","pages":[{"conditions":{"actorHp":50,"actorId":1,"actorValid":false,"enemyHp":50,"enemyIndex":0,"enemyValid":false,"switchId":1,"switchValid":false,"turnA":0,"turnB":0,"turnEnding":false,"turnValid":false},"list":[{"code":0,"indent":0,"parameters":[]}],"span":0}]},
{"id":43,"members":[],"name":"","pages":[{"conditions":{"actorHp":50,"actorId":1,"actorValid":false,"enemyHp":50,"enemyIndex":0,"enemyValid":false,"switchId":1,"switchValid":false,"turnA":0,"turnB":0,"turnEnding":false,"turnValid":false},"list":[{"code":0,"indent":0,"parameters":[]}],"span":0}]},
{"id":44,"members":[],"name":"","pages":[{"conditions":{"actorHp":50,"actorId":1,"actorValid":false,"enemyHp":50,"enemyIndex":0,"enemyValid":false,"switchId":1,"switchValid":false,"turnA":0,"turnB":0,"turnEnding":false,"turnValid":false},"list":[{"code":0,"indent":0,"parameters":[]}],"span":0}]},
{"id":45,"members":[],"name":"","pages":[{"conditions":{"actorHp":50,"actorId":1,"actorValid":false,"enemyHp":50,"enemyIndex":0,"enemyValid":false,"switchId":1,"switchValid":false,"turnA":0,"turnB":0,"turnEnding":false,"turnValid":false},"list":[{"code":0,"indent":0,"parameters":[]}],"span":0}]},
{"id":46,"members":[],"name":"","pages":[{"conditions":{"actorHp":50,"actorId":1,"actorValid":false,"enemyHp":50,"enemyIndex":0,"enemyValid":false,"switchId":1,"switchValid":false,"turnA":0,"turnB":0,"turnEnding":false,"turnValid":false},"list":[{"code":0,"indent":0,"parameters":[]}],"span":0}]},
{"id":47,"members":[],"name":"","pages":[{"conditions":{"actorHp":50,"actorId":1,"actorValid":false,"enemyHp":50,"enemyIndex":0,"enemyValid":false,"switchId":1,"switchValid":false,"turnA":0,"turnB":0,"turnEnding":false,"turnValid":false},"list":[{"code":0,"indent":0,"parameters":[]}],"span":0}]},
{"id":48,"members":[],"name":"","pages":[{"conditions":{"actorHp":50,"actorId":1,"actorValid":false,"enemyHp":50,"enemyIndex":0,"enemyValid":false,"switchId":1,"switchValid":false,"turnA":0,"turnB":0,"turnEnding":false,"turnValid":false},"list":[{"code":0,"indent":0,"parameters":[]}],"span":0}]},
{"id":49,"members":[],"name":"","pages":[{"conditions":{"actorHp":50,"actorId":1,"actorValid":false,"enemyHp":50,"enemyIndex":0,"enemyValid":false,"switchId":1,"switchValid":false,"turnA":0,"turnB":0,"turnEnding":false,"turnValid":false},"list":[{"code":0,"indent":0,"parameters":[]}],"span":0}]},
{"id":50,"members":[],"name":"","pages":[{"conditions":{"actorHp":50,"actorId":1,"actorValid":false,"enemyHp":50,"enemyIndex":0,"enemyValid":false,"switchId":1,"switchValid":false,"turnA":0,"turnB":0,"turnEnding":false,"turnValid":false},"list":[{"code":0,"indent":0,"parameters":[]}],"span":0}]}
]